{"KvmvZV0Bq1wwhfS48gtoMw==":"peru-bike-logotipo-122x74.png","Y+7qz6kxxjoFRxA41j5UdQ==":"peru-bike-logotipo-422x256.png","G7hJoSTmfo0jsddho8Aj1w==":"634f31d32fc2ba2040ad8616cab783e9-1600x900.jpg","JOyyymk3wzuOqxR6/+gfnA==":"mbr-1920x1280.jpg","gmyPAiRBMi477/7ou0G7FQ==":"web0-2000x1328.jpg","5uP8fQm/iXDr0SuJnJ6Zxw==":"lima%20bah%C3%ADa-1280x720.jpg","I95sCd0WIRwqrUSjlMzsOA==":"b-1110x740.jpg","ERAMf6vPFnpDBrBgij06jw==":"lima-2-700x525.jpg","7JhELM6YgrUuAnPX0dDA7g==":"634f31d32fc2ba2040ad8616cab783e9-700x394.jpg","M5e3H6EuDFdYfXFaCmXLIw==":"flyer-700x458.jpg","9uq6isnD37WIPTwAalEUxw==":"colonial-700x525.jpg","dc4GTqwjYvLT91wUhnDxKw==":"playa-700x402.jpg","6oUJX2wY/KBMW7PaB+34ng==":"c-700x732.jpg","0dcReE2D7UWam5H3SH67gw==":"lima-bici-550x367.jpg","iVBYeuhic1Xq/u9cTz93Ng==":"dsc-619-700x467.jpg","wtL3L0DKAM5a35JCSO4xhA==":"playalaisla-700x467.jpg","xW7Rw+HnK9j0shEbqD+91Q==":"lisse%20bike%20rental-1514530984-1515744735-1270x582.jpg","DS3NvTa+IOFb6Bq+4fzasg==":"lisse%20bike%20rental-1514530984-1515744735-1270x582.jpg","pL29NdWj2Utns+R2mwa1xA==":"c-1-700x732.jpg","Kidrwct5xkI0sovVPbHm8g==":"lima-bici-1-550x367.jpg","1gEQX2hJ62VUN3BEY0Rqqg==":"b-700x467.jpg","miotI+c1d7sl1h/Vm8FXrQ==":"mbr-1920x1440.jpg","WLsnGk+DTzZ2l7hxldzfiw==":"peru-lima-1-700x309.jpg","JM64i86nRS1lW9w3kUgu9w==":"b-1-700x467.jpg","srgTXc2Z7DNWAPStMMgKPg==":"lisse%20bike%20rental-1514530984-1515744735-700x321.jpg","hArAuSJHiI80Y1oBY9d6RQ==":"amba-social-lima-page-image-2000x1006.jpg","ImgEm7D/IfcNGhUXEPw5DQ==":"flyer-1888x1235.jpg","xQyTwWxuc01EbPbOriNKHA==":"lisse%20bike%20rental-1514530984-1515744735-1680x770.jpg","C66pOa2MjfzqCLYvYinb9w==":"x8q2ec9-700x525.jpg","VqbvvV6eZw2ZRPdzM1oNJw==":"lima%20bah%C3%ADa-700x394.jpg","eZy+jC4uaFY8aAYrUjG5Ug==":"lima%20bah%C3%ADa-700x394.jpg","t1eeKnTyf3bvgEMV5PijWw==":"634f31d32fc2ba2040ad8616cab783e9-1-700x394.jpg","tJPXWIWinUDTvDMbcYU2NQ==":"634f31d32fc2ba2040ad8616cab783e9-2-700x394.jpg","iWQbboglSBba2tVVdXi28Q==":"flyer-1-700x458.jpg","Ykt/yXUjAdlL+8bcRREH4A==":"dsc-620-700x467.jpg","Nw11YNYMNnXQgyHucnIh5w==":"background3.jpg","7f1wkpfNglwquAn9HMlS3w==":"634f31d32fc2ba2040ad8616cab783e9-1080x608.jpg","TbdJC2vrZTe0mRaPnQuzBA==":"dsc-619-1080x720.jpg","OUUSPzNWxvXQ38eLhYZ0SA==":"flyer-1080x706.jpg","UpJs0eALDDPXwuvyDdcZIA==":"peru-lima-1-1080x477.jpg","OfehXYb4fPWU9+EU/q8NOw==":"peru-lima-1-1200x530.jpg","0k306E2UtsaV7s8HMMnfoA==":"6042357612_fa66ec08bd_o-2000x1368.jpg","Gsm/HTWaRUYQPk6yXVN5Kg==":"000431037w-1800x1232.jpg","WCGLf63hnxdzS8ithcgnWA==":"6042357612_fa66ec08bd_o-1-2000x1368.jpg","cZM2RIyTv+3r+SKJSrKUBA==":"000431037w-1-1800x1232.jpg","T5pF7b7pPTCNpnxbFB2EFw==":"000257754w-1800x1125.jpg","7GP8UxuV1C1tm2w5P/JjzA==":"3-1600x900.jpg","/Qbo1lm9ui30daAaU/lHBw==":"07.jpg","B7cOw/VzKrrpnf5Tlfzoow==":"background1.jpg","n5lTxTvHj3gXwAm3+zmeiQ==":"06.jpg","0HPY1vYYPBBaJxER4bEWzA==":"background1-1.jpg","dvr/ieSYVt10Xgv3urwn5w==":"06-1.jpg","XisDMX379REDa/U4CkmD/A==":"05.jpg","dzMVOS7mmKbz0sKRDb3mrA==":"03.jpg","J+Pt/Oonc1SI8RZ1NMIAIw==":"background4.jpg","dwj0dEPKu53+jfuvVA5AUw==":"634f31d32fc2ba2040ad8616cab783e9-1-1080x608.jpg","s7G8eQzcc5GY7cSr24jlFQ==":"dsc-620-1080x720.jpg","HzVfL46VTQv8ceBlXE5CwA==":"flyer-1-1080x706.jpg","qsgJeTFylc6I1CCdYscbdA==":"peru-lima-2-1080x477.jpg","JYet6x4EUwDthB1X+ZifXg==":"mbr-1-1920x1280.jpg","ewV2kxTtR84UUDwflVNfxQ==":"perubike%20(8)-1280x850.jpg","sNMqVx8rvK3wm1cF/am1Fw==":"perubike%20(13)-1024x768.jpg","JlGG2i6kcFeTUwkiPldK7g==":"perubike%20(2)-1080x608.jpg","slvxdWX5YoqPkCiNGSxTXA==":"perubike%20(6)-1080x719.jpg","UUqz24REqu5+1mHYaPSG8g==":"perubike%20(7)-1080x706.jpg","Fx30jLcCGl6JA5tSmzRIng==":"perubike%20(12)-1080x477.jpg","fulBB0JavNiM1rVi9z7GyQ==":"mbr-1080x810.jpg","5uzuzTLWCGi7PAgbekAl+w==":"mbr-1-1080x810.jpg","zq0vNIl813mzTktXhV6Q9w==":"perubike%20(9)-510x287.jpg","mWYr0zoFqy7h+26Bc6XMoQ==":"perubike%20(9)-510x287.jpg","ilh6mD0jq4PJyrCmnz/QAQ==":"perubike%20(9)-510x287.jpg","mp7ki+SthZ7qlc2QtIXR9w==":"perubike%20(13)-510x383.jpg","td2fXmeydKiz2girr+1FBA==":"perubike%20(11)-510x383.jpg","lr3I7/s2x1zuYGjxtf1W2g==":"jauja%20(7)-1600x700.jpg","qWjxFjAJUbMn1ps2DTgnpA==":"jauja%20(4)-1800x1125.jpg","DCYC9S45KbNnTPPuPoAJUw==":"jauja%20(4)-1800x1125.jpg","egyDXZznGk5jHnfF4Y1kyg==":"jauja%20(6)-1600x899.jpg","KNJeoarvUSrYcSDoC4taYA==":"jauja%20(3)-1276x850.jpg","l6iBbz7697fz73wWUudpGQ==":"jauja%20(2)-1242x850.jpg","iT9MATRnjVx2UGzc2KerwA==":"mbr-1080x720.jpg","NKMb9/bYAEdGvhB6/UwjNw==":"perubike%20(10)-510x234.jpg","cC/Xyned6lVf55qmFL74ow==":"perubike%20(2)-510x287.jpg","MUkyv9kb12pKJgC70Iyqfw==":"perubike%20(12)-510x225.jpg","EXpQ/Mer/BN0l5taMdtzGg==":"mbr-510x383.jpg","gX7S2cWunG5tctn9qOUu9g==":"mbr-1-510x383.jpg"}